{
    "jobs": [
        {
            "title": "RESEARCH LABORATORY COORDINATOR II",
            "school": "Memorial University",
            "date": "2026-01-29T09:00:00",
            "link": "https://www.mun.ca/hr/careers/employment-opportunity/?id=6428",
            "new_since": "2026-01-30T22:52:28.066180"
        },
        {
            "title": "MECHANICAL PATROLPERSON (BAND LEVEL 6)",
            "school": "Memorial University",
            "date": "2026-01-29T09:00:00",
            "link": "https://www.mun.ca/hr/careers/employment-opportunity/?id=6426",
            "new_since": "2026-01-30T22:52:28.066180"
        },
        {
            "title": "Director, Internal Audit",
            "school": "Memorial University",
            "date": "2026-01-29T09:00:00",
            "link": "https://www.mun.ca/hr/careers/employment-opportunity/?id=6424",
            "new_since": "2026-01-30T22:52:28.066180"
        },
        {
            "title": "FACILITIES SERVICES TECHNICIAN (BAND LEVEL 3)",
            "school": "Memorial University",
            "date": "2026-01-27T09:00:00",
            "link": "https://www.mun.ca/hr/careers/employment-opportunity/?id=6421",
            "new_since": "2026-01-30T22:52:28.066180"
        },
        {
            "title": "COORDINATOR, CHEMICAL MANAGEMENT AND ASSURANCE (BAND 10)",
            "school": "Memorial University",
            "date": "2026-01-27T09:00:00",
            "link": "https://www.mun.ca/hr/careers/employment-opportunity/?id=6419",
            "new_since": "2026-01-30T22:52:28.066180"
        },
        {
            "title": "SENIOR INSTRUCTIONAL DESIGNER (BAND 10)",
            "school": "Memorial University",
            "date": "2026-01-23T09:00:00",
            "link": "https://www.mun.ca/hr/careers/employment-opportunity/?id=6416",
            "new_since": "2026-01-25T22:53:23.280997"
        },
        {
            "title": "CARPENTRY APPRENTICE (BAND LEVEL 7)",
            "school": "Memorial University",
            "date": "2026-01-22T09:00:00",
            "link": "https://www.mun.ca/hr/careers/employment-opportunity/?id=6413",
            "new_since": "2026-01-25T22:53:23.280997"
        },
        {
            "title": "INTERMEDIATE SECRETARY (BAND LEVEL 4)",
            "school": "Memorial University",
            "date": "2026-01-21T09:00:00",
            "link": "https://www.mun.ca/hr/careers/employment-opportunity/?id=6407",
            "new_since": "2026-01-25T22:53:23.280997"
        },
        {
            "title": "ACCOUNTING CLERK (BAND LEVEL 4)",
            "school": "Memorial University",
            "date": "2026-01-20T09:00:00",
            "link": "https://www.mun.ca/hr/careers/employment-opportunity/?id=6404",
            "new_since": "2026-01-20T22:52:44.991634"
        },
        {
            "title": "SENIOR SECRETARY (BAND LEVEL 6)",
            "school": "Memorial University",
            "date": "2026-01-19T09:00:00",
            "link": "https://www.mun.ca/hr/careers/employment-opportunity/?id=6402",
            "new_since": "2026-01-20T22:52:44.991634"
        },
        {
            "title": "INSTRUCTOR SCHOOL OF FISHERIES – ELIGIBILITY LIST",
            "school": "Memorial University",
            "date": "2022-07-15T09:00:00",
            "link": "https://www.mun.ca/hr/careers/employment-opportunity/?id=3031",
            "new_since": "2025-01-08T16:44:14.929652"
        },
        {
            "title": "Instructors",
            "school": "Memorial University",
            "date": "2021-04-27T09:00:00",
            "link": "https://www.mun.ca/hr/careers/employment-opportunity/?id=1395",
            "new_since": "2025-01-08T16:44:14.929652"
        },
        {
            "title": "Administrative Temp Opportunities",
            "school": "University of New Brunswick",
            "date": "January 30th, 2026",
            "link": "https://jobs.careerbeacon.com/details/administrative-temp-opportunities/1953773?utm_source=University+of+New+Brunswick&utm_medium=widget&utm_campaign=refer&utm_content=1953773&utm_term=jobtitle",
            "new_since": "2026-01-30T22:52:28.066180"
        },
        {
            "title": "Administrative Temp Opportunities",
            "school": "University of New Brunswick",
            "date": "January 30th, 2026",
            "link": "https://jobs.careerbeacon.com/details/administrative-temp-opportunities/1902601?utm_source=University+of+New+Brunswick&utm_medium=widget&utm_campaign=refer&utm_content=1902601&utm_term=jobtitle",
            "new_since": "2026-01-30T22:52:28.066180"
        },
        {
            "title": "LTA School of Education (Field Placement Coordinator)",
            "school": "St. Thomas University",
            "date": "January 20th, 2026",
            "link": "https://www.stu.ca/media/Advertisement-Field-Placement-Coordinator-Limited-Term-Appointment.docx",
            "new_since": "2026-01-20T22:52:44.991634"
        },
        {
            "title": "Part-Time Position - Education",
            "school": "St. Thomas University",
            "date": "October 17th, 2025",
            "link": "https://www.stu.ca/media/2025-26--Education-5613-Sem-3-External.pdf",
            "new_since": "2025-10-17T20:33:00.108308"
        },
        {
            "title": "CONSEILLÈRE ou CONSEILLER EN ACQUISITION DE TALENTS, Service des ressources humaines",
            "school": "Université de Moncton",
            "date": "January 14, 2026",
            "link": "https://www.careerbeacon.com/fr/emplois/2201148/universite-de-moncton/conseillere-ou-conseiller-en-acquisition-de-talents-service-des-ressources-humaines/moncton-nb?utm_source=careerbeacon",
            "new_since": "2026-01-14T22:52:11.398995"
        },
        {
            "title": "INGÉNIEUR(E) SPÉCIALISÉ(E) EN FORCE MOTRICE XV (Power Engineer)",
            "school": "Université de Moncton",
            "date": "January 14, 2026",
            "link": "https://www.careerbeacon.com/fr/emplois/2199872/universite-de-moncton/ingenieur-e-specialise-e-en-force-motrice-xv-power-engineer/moncton-nb?utm_source=careerbeacon",
            "new_since": "2026-01-14T22:52:11.398995"
        },
        {
            "title": "PROFESSEURE OU PROFESSEUR EN PHILOSOPHIE DES SCIENCES",
            "school": "Université de Moncton",
            "date": "2026-01-06",
            "link": "https://www.careerbeacon.com/fr/emplois/2199544/universite-de-moncton-campus-de-moncton-umcm/professeure-ou-professeur-en-philosophie-des-sciences/moncton-nb?utm_source=careerbeacon",
            "new_since": "2026-01-09T22:52:18.889235"
        },
        {
            "title": "PROFESSEURE OU PROFESSEUR EN BIOLOGIE MARINE",
            "school": "Université de Moncton",
            "date": "November 12, 2025",
            "link": "https://www.careerbeacon.com/fr/emplois/2179975/universite-de-moncton-campus-de-moncton-umcm/professeure-ou-professeur-en-biologie-marine/moncton-nb?utm_source=careerbeacon",
            "new_since": "2025-11-12T22:52:06.999880"
        },
        {
            "title": "TECHNICIENNE ou TECHNICIEN IV, Département de physique et astronomie, Faculté des sciences",
            "school": "Université de Moncton",
            "date": "2026-01-28",
            "link": "https://www.careerbeacon.com/fr/emplois/2203919/universite-de-moncton/technicienne-ou-technicien-iv-departement-de-physique-et-astronomie-faculte-des-sciences/moncton-nb?utm_source=careerbeacon",
            "new_since": "2026-01-30T22:52:28.066180"
        },
        {
            "title": "ASSISTANT(E) ADMINISTRATIF(VE), Service du Logement",
            "school": "Université de Moncton",
            "date": "2026-01-28",
            "link": "https://www.careerbeacon.com/fr/emplois/2202662/universite-de-moncton/assistant-e-administratif-ve-service-du-logement/moncton-nb?utm_source=careerbeacon",
            "new_since": "2026-01-30T22:52:28.066180"
        },
        {
            "title": "PROFESSEURE ou PROFESSEUR EN AUDIT avec possibilité de bourse de recrutement*",
            "school": "Université de Moncton",
            "date": "January 13, 2026",
            "link": "https://www.careerbeacon.com/fr/emplois/2180425/universite-de-moncton-campus-de-moncton-umcm/professeure-ou-professeur-en-audit-avec-possibilite-de-bourse-de-recrutement/moncton-nb?utm_source=careerbeacon",
            "new_since": "2026-01-13T22:52:21.495116"
        },
        {
            "title": "Agente ou agent d’encadrement pour les cours offerts à distance UMCS - site de Bathurst",
            "school": "Université de Moncton",
            "date": "January 15, 2026",
            "link": "https://www.careerbeacon.com/fr/emplois/2201890/universite-de-moncton-campus-de-shippagan-umcs//bathurst-nb?utm_source=careerbeacon",
            "new_since": "2026-01-15T22:52:10.163054"
        },
        {
            "title": "Intervenante ou intervenant psychosocial",
            "school": "Université de Moncton",
            "date": "January 26, 2026",
            "link": "https://www.careerbeacon.com/fr/emplois/2204284/universite-de-moncton-campus-de-shippagan-umcs/intervenante-ou-intervenant-psychosocial/shippagan-nb?utm_source=careerbeacon",
            "new_since": "2026-01-26T22:52:44.042717"
        },
        {
            "title": "Agente ou agent d’encadrement pour les cours offerts à distance - site de Shippagan",
            "school": "Université de Moncton",
            "date": "January 15, 2026",
            "link": "https://www.careerbeacon.com/fr/emplois/2201803/universite-de-moncton-campus-de-shippagan-umcs//shippagan-nb?utm_source=careerbeacon",
            "new_since": "2026-01-15T22:52:10.163054"
        },
        {
            "title": "INTERVENANT(E) PSYCHOSOCIAL(E), Service de santé et psychologie",
            "school": "Université de Moncton",
            "date": "January 26, 2026",
            "link": "https://www.careerbeacon.com/fr/emplois/2204354/universite-de-moncton/intervenant-e-psychosocial-e-service-de-sante-et-psychologie/moncton-nb?utm_source=careerbeacon",
            "new_since": "2026-01-26T22:52:44.042717"
        },
        {
            "title": "Intervenante ou intervenant psychosocial",
            "school": "Université de Moncton",
            "date": "2026-01-22",
            "link": "https://www.careerbeacon.com/fr/emplois/2203556/universite-de-moncton-campus-d-edmundston-umce/intervenante-ou-intervenant-psychosocial/edmundston-nb?utm_source=careerbeacon",
            "new_since": "2026-01-25T22:53:23.282003"
        },
        {
            "title": "CHARGÉE ou CHARGÉ D’ENSEIGNEMENT EN SCIENCE INFIRMIÈRE - INFIRMIÈRE OU INFIRMIER PRATICIEN (IIP)",
            "school": "Université de Moncton",
            "date": "2026-01-12",
            "link": "https://www.careerbeacon.com/fr/emplois/2200910/universite-de-moncton-campus-de-moncton-umcm//moncton-nb?utm_source=careerbeacon",
            "new_since": "2026-01-13T22:52:21.495116"
        },
        {
            "title": "PROFESSEURE OU PROFESSEUR EN DIDACTIQUE DES ARTS VISUELS",
            "school": "Université de Moncton",
            "date": "2026-01-06",
            "link": "https://www.careerbeacon.com/fr/emplois/2194816/universite-de-moncton-campus-de-moncton-umcm/professeure-ou-professeur-en-didactique-des-arts-visuels/moncton-nb?utm_source=careerbeacon",
            "new_since": "2026-01-09T22:52:18.889235"
        },
        {
            "title": "PROFESSEURE ou PROFESSEUR EN COMPTABILITÉ FINANCIÈRE avec possibilité de bourse de recrutement*",
            "school": "Université de Moncton",
            "date": "2025-11-14",
            "link": "https://www.careerbeacon.com/fr/emplois/2190544/universite-de-moncton-campus-de-moncton-umcm/professeure-ou-professeur-en-comptabilite-financiere-avec-possibilite-de-bourse-de-recrutement/moncton-nb?utm_source=careerbeacon",
            "new_since": "2025-11-16T22:52:19.150697"
        },
        {
            "title": "AGENTE ou AGENT DE SÉCURITÉ (temporaire 4 mois)",
            "school": "Université de Moncton",
            "date": "January 14, 2026",
            "link": "https://www.careerbeacon.com/fr/emplois/2201256/universite-de-moncton/agente-ou-agent-de-securite-temporaire-4-mois/moncton-nb?utm_source=careerbeacon",
            "new_since": "2026-01-14T22:52:11.398995"
        },
        {
            "title": "COMPTABLE ANALYSTE, Recherche et Fiducie",
            "school": "Université de Moncton",
            "date": "2026-01-28",
            "link": "https://www.careerbeacon.com/fr/emplois/2202947/universite-de-moncton/comptable-analyste-recherche-et-fiducie/moncton-nb?utm_source=careerbeacon",
            "new_since": "2026-01-30T22:52:28.066180"
        },
        {
            "title": "AGENT(E) DE SÉCURITÉ, Service de sécurité, 2 postes disponibles",
            "school": "Université de Moncton",
            "date": "2026-01-28",
            "link": "https://www.careerbeacon.com/fr/emplois/2202664/universite-de-moncton/agent-e-de-securite-service-de-securite-2-postes-disponibles/moncton-nb?utm_source=careerbeacon",
            "new_since": "2026-01-30T22:52:28.066180"
        },
        {
            "title": "ÉLECTRICIENNE ou ÉLECTRICIEN XIV (temporaire 2 ans)",
            "school": "Université de Moncton",
            "date": "2026-01-28",
            "link": "https://www.careerbeacon.com/fr/emplois/2190332/universite-de-moncton/electricienne-ou-electricien-xiv-temporaire-2-ans/moncton-nb?utm_source=careerbeacon",
            "new_since": "2026-01-30T22:52:28.066180"
        },
        {
            "title": "DIRECTION ADJOINTE, Service de sécurité",
            "school": "Université de Moncton",
            "date": "2026-01-28",
            "link": "https://www.careerbeacon.com/fr/emplois/2193986/universite-de-moncton/direction-adjointe-service-de-securite/moncton-nb?utm_source=careerbeacon",
            "new_since": "2026-01-30T22:52:28.066180"
        },
        {
            "title": "ASSISTANT(E) VII, Faculté de droit",
            "school": "Université de Moncton",
            "date": "2026-01-28",
            "link": "https://www.careerbeacon.com/fr/emplois/2202951/universite-de-moncton/assistant-e-vii-faculte-de-droit/moncton-nb?utm_source=careerbeacon",
            "new_since": "2026-01-30T22:52:28.066180"
        },
        {
            "title": "PRÉPOSÉE ou PRÉPOSÉ À L'ADMISSION",
            "school": "Université de Moncton",
            "date": "2026-01-28",
            "link": "https://www.careerbeacon.com/fr/emplois/2202948/universite-de-moncton/preposee-ou-prepose-a-l-admission/moncton-nb?utm_source=careerbeacon",
            "new_since": "2026-01-30T22:52:28.066180"
        },
        {
            "title": "TECHNICIENNE ou TECHNICEN DU LABORATOIRE DE MICROBIOLOGIE ET DE CHIMIE",
            "school": "Université de Moncton",
            "date": "2026-01-28",
            "link": "https://www.careerbeacon.com/fr/emplois/2201598/universite-de-moncton/technicienne-ou-technicen-du-laboratoire-de-microbiologie-et-de-chimie/moncton-nb?utm_source=careerbeacon",
            "new_since": "2026-01-30T22:52:28.066180"
        },
        {
            "title": "ANALYSTE – Gestion des données et rapports",
            "school": "Université de Moncton",
            "date": "2026-01-28",
            "link": "https://www.careerbeacon.com/fr/emplois/2202953/universite-de-moncton//moncton-nb?utm_source=careerbeacon",
            "new_since": "2026-01-30T22:52:28.066180"
        },
        {
            "title": "SUMMER 2026 CO-OP – CAMP ACTIVITIES DIRECTOR – KLAHANIE KAMPING – AYLESFORD, NS",
            "school": "Cape Breton University",
            "link": "https://www.cbu.ca/current-students/student-services/career-services/student-job-opportunities/summer-2026-co-op-camp-activities-director-klahanie-kamping-aylesford-ns/",
            "date": "January 9th, 2026",
            "new_since": "2026-01-09T22:52:18.889235"
        },
        {
            "title": "RECENT OR POTENTIAL GRADS: THE PARLIAMENTARY INTERNSHIP PROGRAMME",
            "school": "Cape Breton University",
            "link": "https://www.cbu.ca/current-students/student-services/career-services/student-job-opportunities/recent-or-potential-grads-the-parliamentary-internship-programme/",
            "date": "January 9th, 2026",
            "new_since": "2026-01-09T22:52:18.889235"
        },
        {
            "title": "SUMMER EMPLOYMENT 2026: INTERPRETER",
            "school": "Cape Breton University",
            "date": "January 30th, 2026",
            "link": "https://www.cbu.ca/current-students/student-services/career-services/student-job-opportunities/summer-employment-2026-interpreter/",
            "new_since": "2026-01-30T22:52:28.066180"
        },
        {
            "title": "NEW GRAD OPPORTUNITY – CHILD PROTECTION SOCIAL WORKER – OPPORTUNITIES AND SOCIAL DEVELOPMENT – HALIFAX, DARTMOUTH, SACKVILLE, NS",
            "school": "Cape Breton University",
            "link": "https://www.cbu.ca/current-students/student-services/career-services/student-job-opportunities/new-grad-opportunity-child-protection-social-worker-opportunities-and-social-development-halifax-dartmouth-sackville-ns/",
            "date": "January 20th, 2026",
            "new_since": "2026-01-20T22:52:44.991634"
        },
        {
            "title": "WORK STUDY WINTER 2026: SOCIAL MEDIA & NEWSLETTER COORDINATOR, SCHOOL OF SCIENCE & TECHNOLOGY",
            "school": "Cape Breton University",
            "date": "January 30th, 2026",
            "link": "https://www.cbu.ca/current-students/student-services/career-services/student-job-opportunities/work-study-winter-2026-social-media-newsletter-coordinator-the-the-school-of-science-technology/",
            "new_since": "2026-01-30T22:52:28.066180"
        },
        {
            "title": "WORK STUDY WINTER 2026: MARKETING AND RECRUITMENT RESEARCH ASSISTANT",
            "school": "Cape Breton University",
            "date": "January 30th, 2026",
            "link": "https://www.cbu.ca/current-students/student-services/career-services/student-job-opportunities/work-study-winter-2026-marketing-and-recruitment-research-assistant/",
            "new_since": "2026-01-30T22:52:28.066180"
        },
        {
            "title": "SUMMER EMPLOYMENT OPPORTUNITY – STUDENT PUBLIC HEALTH INSPECTOR PRACTICUM POSITION – SOUTHEAST PUBLIC HEALTH – VARIOUS LOCATIONS, ON",
            "school": "Cape Breton University",
            "date": "January 30th, 2026",
            "link": "https://www.cbu.ca/current-students/student-services/career-services/student-job-opportunities/summer-employment-opportunity-student-public-health-inspector-practicum-position-southeast-public-health-various-locations-on/",
            "new_since": "2026-01-30T22:52:28.066180"
        },
        {
            "title": "SUMMER 2026: MANAGEMENT TRAINEE SUMMER INTERNSHIP",
            "school": "Cape Breton University",
            "link": "https://www.cbu.ca/current-students/student-services/career-services/student-job-opportunities/summer-2026-management-trainee-summer-internship/",
            "date": "January 20th, 2026",
            "new_since": "2026-01-20T22:52:44.991634"
        },
        {
            "title": "NEW GRAD OPPORTUNITY – CHILD AND YOUTH CARE PRACTITIONER – OPPORTUNITIES AND SOCIAL DEVELOPMENT – SYDNEY, NS",
            "school": "Cape Breton University",
            "date": "January 30th, 2026",
            "link": "https://www.cbu.ca/current-students/student-services/career-services/student-job-opportunities/150084/",
            "new_since": "2026-01-30T22:52:28.066180"
        },
        {
            "title": "RECENT OR POTENTIAL GRADS: COUNCIL OF THE FEDERATION INTERNSHIP PROGRAM",
            "school": "Cape Breton University",
            "link": "https://www.cbu.ca/current-students/student-services/career-services/student-job-opportunities/recent-or-potential-grads-council-of-the-federation-internship-program/",
            "date": "January 25th, 2026",
            "new_since": "2026-01-25T22:53:23.282003"
        },
        {
            "title": "SUMMER 2026 – CIVIL ENGINEERING STUDENT – GULF OPERATORS – SAINT JOHN, NB",
            "school": "Cape Breton University",
            "link": "https://www.cbu.ca/current-students/student-services/career-services/student-job-opportunities/summer-2026-civil-engineering-student-gulf-operators-saint-john-nb/",
            "date": "January 26th, 2026",
            "new_since": "2026-01-26T22:52:44.042717"
        },
        {
            "title": "SUMMER 2026 – ACCOUNTING STUDENT – J.D. IRVING CONSTRUCTION AND EQUIPMENT DIVISION – SAINT JOHN, NB",
            "school": "Cape Breton University",
            "link": "https://www.cbu.ca/current-students/student-services/career-services/student-job-opportunities/summer-2026-accounting-student-j-d-irving-construction-and-equipment-division-saint-john-nb/",
            "date": "January 26th, 2026",
            "new_since": "2026-01-26T22:52:44.042717"
        },
        {
            "title": "Executive Assistant to the Dean",
            "school": "Dalhousie University",
            "date": "January 30th, 2026",
            "link": "https://dal.peopleadmin.ca/postings/20199",
            "new_since": "2026-01-30T22:52:28.066180"
        },
        {
            "title": "Postdoctoral Fellow in the Physics of Aging",
            "school": "Dalhousie University",
            "date": "January 30th, 2026",
            "link": "https://dal.peopleadmin.ca/postings/20194",
            "new_since": "2026-01-30T22:52:28.066180"
        },
        {
            "title": "Administrative Assistant",
            "school": "Dalhousie University",
            "link": "https://dal.peopleadmin.ca/postings/20182",
            "date": "January 26th, 2026",
            "new_since": "2026-01-26T22:52:44.042717"
        },
        {
            "title": "Clinician Scientist, Pediatric Infectious Diseases",
            "school": "Dalhousie University",
            "link": "https://dal.peopleadmin.ca/postings/20181",
            "date": "January 26th, 2026",
            "new_since": "2026-01-26T22:52:44.042717"
        },
        {
            "title": "Accounts Payable Clerk",
            "school": "Dalhousie University",
            "link": "https://dal.peopleadmin.ca/postings/20180",
            "date": "January 25th, 2026",
            "new_since": "2026-01-25T22:53:23.282003"
        },
        {
            "title": "Clinical Program Assistant",
            "school": "Dalhousie University",
            "link": "https://dal.peopleadmin.ca/postings/20179",
            "date": "January 25th, 2026",
            "new_since": "2026-01-25T22:53:23.282003"
        },
        {
            "title": "Research Assistant",
            "school": "Dalhousie University",
            "link": "https://dal.peopleadmin.ca/postings/20178",
            "date": "January 25th, 2026",
            "new_since": "2026-01-25T22:53:23.282003"
        },
        {
            "title": "Postdoctoral Fellow in Frailty, Aging, and Cardiovascular Health",
            "school": "Dalhousie University",
            "link": "https://dal.peopleadmin.ca/postings/20175",
            "date": "January 25th, 2026",
            "new_since": "2026-01-25T22:53:23.282003"
        },
        {
            "title": "Talent Pathways - Candidate Roster for Temporary Positions",
            "school": "Dalhousie University",
            "link": "https://dal.peopleadmin.ca/postings/20168",
            "date": "January 25th, 2026",
            "new_since": "2026-01-25T22:53:23.282003"
        },
        {
            "title": "Part-Time Academic (LARC1010 - Studio I: Introduction to Design at FAFU, China) - Spring 2026",
            "school": "Dalhousie University",
            "link": "https://dal.peopleadmin.ca/postings/20167",
            "date": "January 25th, 2026",
            "new_since": "2026-01-25T22:53:23.282003"
        },
        {
            "title": "Electrician (Term)",
            "school": "Dalhousie University",
            "link": "https://dal.peopleadmin.ca/postings/20166",
            "date": "January 25th, 2026",
            "new_since": "2026-01-25T22:53:23.282003"
        },
        {
            "title": "Steamfitter",
            "school": "Dalhousie University",
            "link": "https://dal.peopleadmin.ca/postings/20164",
            "date": "January 25th, 2026",
            "new_since": "2026-01-25T22:53:23.282003"
        },
        {
            "title": "Chair in Medical Education Research",
            "school": "Dalhousie University",
            "link": "https://dal.peopleadmin.ca/postings/20161",
            "date": "January 20th, 2026",
            "new_since": "2026-01-20T22:52:44.991634"
        },
        {
            "title": "Instructor (Faculty of Law)",
            "school": "Dalhousie University",
            "link": "https://dal.peopleadmin.ca/postings/20156",
            "date": "January 20th, 2026",
            "new_since": "2026-01-20T22:52:44.991634"
        },
        {
            "title": "Director, Tax Dispute Clinic",
            "school": "Dalhousie University",
            "link": "https://dal.peopleadmin.ca/postings/20138",
            "date": "January 13th, 2026",
            "new_since": "2026-01-13T22:52:21.495116"
        },
        {
            "title": "Financial Analyst",
            "school": "Dalhousie University",
            "link": "https://dal.peopleadmin.ca/postings/20135",
            "date": "January 13th, 2026",
            "new_since": "2026-01-13T22:52:21.495116"
        },
        {
            "title": "Chief Administrative Officer",
            "school": "Dalhousie University",
            "link": "https://dal.peopleadmin.ca/postings/20129",
            "date": "January 9th, 2026",
            "new_since": "2026-01-09T22:52:18.889235"
        },
        {
            "title": "Director, School of Nursing/Assistant Dean, Faculty of Health",
            "school": "Dalhousie University",
            "link": "https://dal.peopleadmin.ca/postings/20126",
            "date": "January 9th, 2026",
            "new_since": "2026-01-09T22:52:18.889235"
        },
        {
            "title": "University Veterinarian",
            "school": "Dalhousie University",
            "link": "https://dal.peopleadmin.ca/postings/20117",
            "date": "January 9th, 2026",
            "new_since": "2026-01-09T22:52:18.889235"
        },
        {
            "title": "Tier 2 Canada Research Chair in Indigenous Prosperity",
            "school": "Dalhousie University",
            "link": "https://dal.peopleadmin.ca/postings/20106",
            "date": "December 24th, 2025",
            "new_since": "2025-12-24T22:51:41.233357"
        },
        {
            "title": "Canada Research Chair",
            "school": "Dalhousie University",
            "link": "https://dal.peopleadmin.ca/postings/20096",
            "date": "December 19th, 2025",
            "new_since": "2025-12-19T22:51:40.685561"
        },
        {
            "title": "Maternal Fetal Medicine Sub-specialist",
            "school": "Dalhousie University",
            "link": "https://dal.peopleadmin.ca/postings/20051",
            "date": "December 19th, 2025",
            "new_since": "2025-12-19T22:51:40.686859"
        },
        {
            "title": "Part-Time Academic (Clinical Instructors for Nursing) - Winter 2026",
            "school": "Dalhousie University",
            "link": "https://dal.peopleadmin.ca/postings/20004",
            "date": "November 28th, 2025",
            "new_since": "2025-11-28T22:51:57.239664"
        },
        {
            "title": "Dean, Faculty of Computer Science (Internal Posting)",
            "school": "Dalhousie University",
            "link": "https://dal.peopleadmin.ca/postings/19987",
            "date": "November 26th, 2025",
            "new_since": "2025-11-26T22:51:56.891008"
        },
        {
            "title": "Assistant Vice-President Equity, Diversity, Inclusion, Accessibility and Belonging",
            "school": "Dalhousie University",
            "link": "https://dal.peopleadmin.ca/postings/19591",
            "date": "October 17th, 2025",
            "new_since": "2025-10-17T20:33:00.108308"
        },
        {
            "title": "Custodian (Term)",
            "school": "Dalhousie University",
            "link": "https://dal.peopleadmin.ca/postings/17151",
            "date": "January 8th, 2025",
            "new_since": "2025-01-08T16:44:14.929652"
        },
        {
            "title": "Part-Time Academic Lab Instructor (Multiple Positions) PHYT 6115: Musculoskeletal Physiotherapy III - Fall 2023",
            "school": "Dalhousie University",
            "link": "https://dal.peopleadmin.ca/postings/14128",
            "date": "January 8th, 2025",
            "new_since": "2025-01-08T16:44:14.929652"
        },
        {
            "title": "Executive Assistant - Governance",
            "school": "NSCAD University",
            "link": "https://jobs.careerbeacon.com/details/executive-assistant--governance/2196537",
            "date": "December 19th, 2025",
            "new_since": "2025-12-19T22:51:40.686859"
        },
        {
            "title": "Animatrices/Animateurs (écoles d'immersion du printemps et d'été)",
            "school": "Université Sainte-Anne",
            "link": "https://www.usainteanne.ca/offres-demploi/sa2026-02",
            "date": "2069-01-20T00:00:00",
            "new_since": "2026-01-20T22:52:44.991634"
        },
        {
            "title": "Professeures/Professeurs de français langue seconde (écoles d'immersion du printemps et d'été)",
            "school": "Université Sainte-Anne",
            "link": "https://www.usainteanne.ca/offres-demploi/sa2026-01",
            "date": "0102-01-20T00:00:00",
            "new_since": "2026-01-20T22:52:44.991634"
        },
        {
            "title": "Superviseure/Superviseur aquatique",
            "school": "Université Sainte-Anne",
            "link": "https://www.usainteanne.ca/offres-demploi/sa2025-36",
            "date": "2025-11-06T00:00:00",
            "new_since": "2025-11-04T22:51:47.279156"
        },
        {
            "title": "Constitution d’une banque de personnes-ressources - Préposé.e à l’accueil",
            "school": "Université Sainte-Anne",
            "link": "https://www.usainteanne.ca/offres-demploi/sa2025-35",
            "date": "2025-10-21T00:00:00",
            "new_since": "2025-10-28T22:51:58.180152"
        },
        {
            "title": "Enseignant/Enseignante de français langue seconde",
            "school": "Université Sainte-Anne",
            "link": "https://www.usainteanne.ca/offres-demploi/sa2303-02",
            "date": "4631-01-08T00:00:00",
            "new_since": "2025-01-08T16:44:14.929652"
        },
        {
            "title": "President & Vice-Chancellor",
            "school": "University of King's College",
            "date": "November 25th, 2025",
            "link": "https://ukings.ca/campus-community/employment/president-and-vice-chancellor/",
            "new_since": "2025-11-25T22:51:54.431483"
        },
        {
            "title": "Residence Assistant/Instructor - Florence Field Course",
            "school": "University of King's College",
            "date": "January 20th, 2026",
            "link": "https://ukings.ca/campus-community/employment/residence-assistant-instructor-florence/",
            "new_since": "2026-01-20T22:52:44.991634"
        },
        {
            "title": "Varsity Head Coach - Men's Soccer",
            "school": "University of King's College",
            "date": "January 20th, 2026",
            "link": "https://ukings.ca/campus-community/employment/varsity-head-coach-mens-soccer/",
            "new_since": "2026-01-20T22:52:44.991634"
        },
        {
            "title": "Senior Fellow in the Humanities in the Foundation Year Program",
            "school": "University of King's College",
            "date": "January 25th, 2026",
            "link": "https://ukings.ca/campus-community/employment/senior-fellow-in-the-humanities/",
            "new_since": "2026-01-25T22:53:23.282003"
        },
        {
            "title": "Faculty Fellow in the Humanities in the Foundation Year Program",
            "school": "University of King's College",
            "date": "January 25th, 2026",
            "link": "https://ukings.ca/campus-community/employment/faculty-fellowship/",
            "new_since": "2026-01-25T22:53:23.282003"
        },
        {
            "school": "University of Prince Edward Island",
            "title": "Bachelor Of Education School And Community Liaison - Faculty of Education",
            "link": "https://www.upei.ca/hr/competition/14e26",
            "date": "Closing date: 2026-02-08T00:00:00",
            "new_since": "2026-01-30T22:52:28.066180"
        },
        {
            "school": "University of Prince Edward Island",
            "title": "Finance Officer - Atlantic Veterinary College",
            "link": "https://www.upei.ca/hr/competition/18e26",
            "date": "Closing date: 2026-02-08T00:00:00",
            "new_since": "2026-01-30T22:52:28.066180"
        },
        {
            "school": "University of Prince Edward Island",
            "title": "Security Attendant (5 Positions) - Security Services Division - Department of Facilities Management",
            "link": "https://www.upei.ca/hr/competition/12e26",
            "date": "Closing date: 2026-02-08T00:00:00",
            "new_since": "2026-01-30T22:52:28.066180"
        },
        {
            "school": "University of Prince Edward Island",
            "title": "Graduate Research Assistant - Institute of Island Studies - Faculty of Arts",
            "link": "https://www.upei.ca/hr/competition/07s26",
            "date": "Closing date: 2026-03-08T00:00:00",
            "new_since": "2026-01-30T22:52:28.066180"
        },
        {
            "school": "University of Prince Edward Island",
            "title": "Sessional Instructors - Faculty of Education - Summer 2026",
            "link": "https://www.upei.ca/hr/competition/14si26",
            "date": "Closing date: 2026-02-12T00:00:00",
            "new_since": "2026-01-30T22:52:28.066180"
        },
        {
            "school": "University of Prince Edward Island",
            "title": "MTS Level 9 - Engineering Projects Coordinator - Faculty of Sustainable Design Engineering",
            "link": "https://www.upei.ca/hr/competition/17e26",
            "date": "Closing date: 2026-02-04T00:00:00",
            "new_since": "2026-01-30T22:52:28.066180"
        },
        {
            "school": "University of Prince Edward Island",
            "title": "Post-Doctoral Research Associate - School of Climate Change and Adaptation - Faculty of Science",
            "link": "https://www.upei.ca/hr/competition/06a26",
            "date": "Closing date: 2026-02-11T00:00:00",
            "new_since": "2026-01-30T22:52:28.066180"
        },
        {
            "school": "University of Prince Edward Island",
            "title": "EAL Instructors (Up to 3 Positions) - International Customized Programs Office - Student Experience Hub",
            "link": "https://www.upei.ca/hr/competition/09e26",
            "date": "Closing date: 2026-02-11T00:00:00",
            "new_since": "2026-01-30T22:52:28.066180"
        },
        {
            "school": "University of Prince Edward Island",
            "title": "MTS Level 6 - Registered Veterinary Technician - Small Animal Operating Room and Surgery Float Technician - Veterinary Teaching Hospital - Atlantic Veterinary College",
            "link": "https://www.upei.ca/hr/competition/13e26",
            "date": "Closing date: 2026-02-15T00:00:00",
            "new_since": "2026-01-26T22:52:44.043731"
        },
        {
            "school": "University of Prince Edward Island",
            "title": "ADS Level 5 - Administrative Assistant - Department of Applied Human Sciences - Faculty of Science",
            "link": "https://www.upei.ca/hr/competition/15e26",
            "date": "Closing date: 2026-02-02T00:00:00",
            "new_since": "2026-01-26T22:52:44.043731"
        },
        {
            "school": "University of Prince Edward Island",
            "title": "ADS Level 6 - Data Control - Banking Clerk - Financial Services Office",
            "link": "https://www.upei.ca/hr/competition/16e26",
            "date": "Closing date: 2026-02-02T00:00:00",
            "new_since": "2026-01-26T22:52:44.043731"
        },
        {
            "school": "University of Prince Edward Island",
            "title": "Sessional Instructor - Faculty of Arts - Department of Diversity and Social Justice Studies (DSJS) - Summer 2026",
            "link": "https://www.upei.ca/hr/competition/13si26",
            "date": "Closing date: 2026-02-06T00:00:00",
            "new_since": "2026-01-25T22:53:23.282003"
        },
        {
            "school": "University of Prince Edward Island",
            "title": "Sessional Instructor- Faculty of Arts - Department of Arts - Summer 2026",
            "link": "https://www.upei.ca/hr/competition/12si26",
            "date": "Closing date: 2026-02-06T00:00:00",
            "new_since": "2026-01-25T22:53:23.282003"
        },
        {
            "school": "University of Prince Edward Island",
            "title": "Sessional Instructor - Faculty of Nursing - Summer 2026",
            "link": "https://www.upei.ca/hr/competition/11si26",
            "date": "Closing date: 2026-02-06T00:00:00",
            "new_since": "2026-01-25T22:53:23.282003"
        },
        {
            "school": "University of Prince Edward Island",
            "title": "Sessional Instructor - Faculty of Nursing - Summer 2026",
            "link": "https://www.upei.ca/hr/competition/10si26",
            "date": "Closing date: 2026-02-06T00:00:00",
            "new_since": "2026-01-25T22:53:23.282003"
        },
        {
            "school": "University of Prince Edward Island",
            "title": "MTS Level 6 with a Market Adjustment to MTS Level 8 - Medical Laboratory Technologist - Clinical Pathology - Diagnostic Services - Atlantic Veterinary College",
            "link": "https://www.upei.ca/hr/competition/231e25r",
            "date": "Closing date: 2026-02-01T00:00:00",
            "new_since": "2026-01-25T22:53:23.282003"
        },
        {
            "school": "University of Prince Edward Island",
            "title": "Sessional Instructor - Faculty of Arts - Department of Island Studies - Summer 2026",
            "link": "https://www.upei.ca/hr/competition/09si26",
            "date": "Closing date: 2026-02-05T00:00:00",
            "new_since": "2026-01-25T22:53:23.282003"
        },
        {
            "school": "University of Prince Edward Island",
            "title": "Sessional Instructor - Faculty of Arts - Department of Psychology - Summer 2026",
            "link": "https://www.upei.ca/hr/competition/08si26",
            "date": "Closing date: 2026-02-05T00:00:00",
            "new_since": "2026-01-25T22:53:23.282003"
        },
        {
            "school": "University of Prince Edward Island",
            "title": "Sessional Instructor - Faculty of Science - Department of Biology - Summer 2026",
            "link": "https://www.upei.ca/hr/competition/07si26",
            "date": "Closing date: 2026-02-05T00:00:00",
            "new_since": "2026-01-25T22:53:23.282003"
        },
        {
            "school": "University of Prince Edward Island",
            "title": "Sessional Instructor - Faculty of Science - Department of Environmental Studies - Summer 2026",
            "link": "https://www.upei.ca/hr/competition/02si26",
            "date": "Closing date: 2026-02-05T00:00:00",
            "new_since": "2026-01-25T22:53:23.282003"
        },
        {
            "school": "University of Prince Edward Island",
            "title": "Sessional Instructors - McDougall Faculty of Business - Summer 2026",
            "link": "https://www.upei.ca/hr/competition/06si26",
            "date": "Closing date: 2026-02-05T00:00:00",
            "new_since": "2026-01-25T22:53:23.282003"
        },
        {
            "school": "University of Prince Edward Island",
            "title": "Sessional Instructor - Faculty of Science- School of Mathematical and Computational Sciences - Summer 2026",
            "link": "https://www.upei.ca/hr/competition/05si26",
            "date": "Closing date: 2026-02-05T00:00:00",
            "new_since": "2026-01-25T22:53:23.282003"
        },
        {
            "school": "University of Prince Edward Island",
            "title": "Sessional Instructor - Faculty of Science - Department of Chemistry - Summer 2026",
            "link": "https://www.upei.ca/hr/competition/04si26",
            "date": "Closing date: 2026-02-05T00:00:00",
            "new_since": "2026-01-25T22:53:23.282003"
        },
        {
            "school": "University of Prince Edward Island",
            "title": "Sessional Instructor- Department of Master of Cleantech Leadership & Transformation - Faculty of Graduate Studies - Summer (1st session) 2026",
            "link": "https://www.upei.ca/hr/competition/01si26",
            "date": "Closing date: 2026-02-28T00:00:00",
            "new_since": "2026-01-20T22:52:44.991634"
        },
        {
            "school": "University of Prince Edward Island",
            "title": "Clinical Nursing Instructor - Faculty of Nursing- 1.0 FTE Permanent Twelve Month Position - Psychiatric Mental Health Nursing (Queen Elizabeth Hospital), Community Nursing and Clinical Support",
            "link": "https://www.upei.ca/hr/competition/05a26",
            "date": "Closing date: 2026-02-02T00:00:00",
            "new_since": "2026-01-20T22:52:44.991634"
        },
        {
            "school": "University of Prince Edward Island",
            "title": "Clinical Nursing Instructor - Faculty of Nursing - 1.0 FTE Permanent Twelve Month Position - Faculty of Nursing Learning Resource Centre",
            "link": "https://www.upei.ca/hr/competition/04a26",
            "date": "Closing date: 2026-02-02T00:00:00",
            "new_since": "2026-01-20T22:52:44.991634"
        },
        {
            "school": "University of Prince Edward Island",
            "title": "Associate Professor - Tenure Track Position - Impact & Talent Research Chair - Office of the Vice President, Academic & Research",
            "link": "https://www.upei.ca/hr/competition/03a26",
            "date": "Closing date: 2026-05-15T00:00:00",
            "new_since": "2026-01-13T22:52:21.495116"
        },
        {
            "school": "University of Prince Edward Island",
            "title": "Clinical Veterinarian - Ambulatory Equine Service (AES) - Veterinary Teaching Hospital - Atlantic Veterinary College - Term Position",
            "link": "https://www.upei.ca/hr/competition/02a26",
            "date": "Closing date: 2026-01-21T00:00:00",
            "new_since": "2026-01-09T22:52:18.890229"
        },
        {
            "school": "University of Prince Edward Island",
            "title": "Sessional Instructor - Department of Psychology - Faculty of Arts (Winter 2026)",
            "link": "https://www.upei.ca/hr/competition/135si25",
            "date": "Closing date: 2026-01-06T00:00:00",
            "new_since": "2025-12-24T22:51:41.234359"
        },
        {
            "school": "University of Prince Edward Island",
            "title": "Sessional Instructors - Department of Psychology - Faculty of Arts (Winter 2026)",
            "link": "https://www.upei.ca/hr/competition/136si25",
            "date": "Closing date: 2026-01-06T00:00:00",
            "new_since": "2025-12-24T22:51:41.234359"
        },
        {
            "school": "University of Prince Edward Island",
            "title": "Associate Dean - Clinical Affairs - AVC Deans Office - Atlantic Veterinary College *Internal Posting Only*",
            "link": "https://www.upei.ca/hr/competition/52a25",
            "date": "Closing date: 2026-01-15T00:00:00",
            "new_since": "2025-12-22T22:51:42.323306"
        },
        {
            "school": "University of Prince Edward Island",
            "title": "Clinical Nursing Instructor - Faculty of Nursing- 0.8 FTE Permanent Ten (10) Month Position - UPEI Faculty of Nursing Learning Resource Centre",
            "link": "https://www.upei.ca/hr/competition/56a25",
            "date": "Closing date: 2026-01-02T00:00:00",
            "new_since": "2025-12-19T22:51:40.686859"
        },
        {
            "school": "University of Prince Edward Island",
            "title": "Clinical Nursing Instructor - Faculty of Nursing- 1.0 FTE Permanent Position - Medical-Surgical Nursing (Queen Elizabeth Hospital)",
            "link": "https://www.upei.ca/hr/competition/55a25",
            "date": "Closing date: 2025-12-31T00:00:00",
            "new_since": "2025-12-19T22:51:40.686859"
        },
        {
            "school": "University of Prince Edward Island",
            "title": "Radiology/Diagnostic Imaging - Tenure Track Position - Department of Companion Animals - Atlantic Veterinary College",
            "link": "https://www.upei.ca/hr/competition/54a25",
            "date": "Closing date: 2026-01-30T00:00:00",
            "new_since": "2025-12-19T22:51:40.686859"
        },
        {
            "school": "University of Prince Edward Island",
            "title": "Clinical Nursing Instructor - Faculty of Nursing- 0.6 FTE Permanent Ten (10) Month Position - Psychiatric Mental Health Nursing (Prince County Hospital), Long-Term Care & Clinical Support *Amended Start Date*",
            "link": "https://www.upei.ca/hr/competition/53a25",
            "date": "Closing date: 2025-12-24T00:00:00",
            "new_since": "2025-12-19T22:51:40.686859"
        },
        {
            "school": "University of Prince Edward Island",
            "title": "Diagnostic Virologist - Department of Diagnostic Services - Atlantic Veterinary College",
            "link": "https://www.upei.ca/hr/competition/51a25",
            "date": "Closing date: 2025-12-23T00:00:00",
            "new_since": "2025-12-19T22:51:40.686859"
        },
        {
            "school": "University of Prince Edward Island",
            "title": "Lecturer - Term Position - Small Animal Emergency & Critical Care - Department of Companion Animals - Atlantic Veterinary College",
            "link": "https://www.upei.ca/hr/competition/46a25",
            "date": "Closing date: 2026-01-06T00:00:00",
            "new_since": "2025-11-27T22:51:52.217955"
        },
        {
            "school": "University of Prince Edward Island",
            "title": "Sessional Instructor - School of Climate Change and Adaptation - Faculty of Science - Winter 2026",
            "link": "https://www.upei.ca/hr/competition/127si25",
            "date": "Closing date: 2025-12-01T00:00:00",
            "new_since": "2025-11-27T22:51:52.217955"
        },
        {
            "school": "University of Prince Edward Island",
            "title": "Assistant Professor - Tenure-Track Position - Faculty of Indigenous Knowledge, Education, Research & Applied Studies",
            "link": "https://www.upei.ca/hr/competition/48a25",
            "date": "Closing date: 2025-11-28T00:00:00",
            "new_since": "2025-11-27T22:51:52.217955"
        },
        {
            "school": "University of Prince Edward Island",
            "title": "Associate Professor - Tenure-Track Position- Faculty of Indigenous Knowledge, Education, Research & Applied Studies",
            "link": "https://www.upei.ca/hr/competition/47a25",
            "date": "Closing date: 2025-11-28T00:00:00",
            "new_since": "2025-11-27T22:51:52.217955"
        },
        {
            "school": "University of Prince Edward Island",
            "title": "MTS Level 3 - Kennel Assistant - Veterinary Teaching Hospital - Atlantic Veterinary College *To Create a Casual List*",
            "link": "https://www.upei.ca/hr/competition/180e25",
            "date": "Closing date: 2026-04-30T00:00:00",
            "new_since": "2025-11-27T22:51:52.217955"
        },
        {
            "school": "University of Prince Edward Island",
            "title": "Tenure Track Position - Department of Psychology - Faculty of Arts *Reposted* *Amended Closing Date*",
            "link": "https://www.upei.ca/hr/competition/14a24",
            "date": "Closing date: 2025-10-09T00:00:00",
            "new_since": "2025-11-27T22:51:52.217955"
        },
        {
            "school": "University of Prince Edward Island",
            "title": "Tenure Track Position - Department of Psychology - Faculty of Arts *Reposted* *Amended Closing Date*",
            "link": "https://www.upei.ca/hr/competition/13a24",
            "date": "Closing date: 2025-10-09T00:00:00",
            "new_since": "2025-11-27T22:51:52.217955"
        },
        {
            "school": "University of Prince Edward Island",
            "title": "Student Assistants - To Create a Casual List - Veterinary Teaching Hospital - Atlantic Veterinary College",
            "link": "https://www.upei.ca/hr/competition/65s25",
            "date": "Closing date: 2026-04-30T00:00:00",
            "new_since": "2025-11-27T22:51:52.217955"
        },
        {
            "school": "University of Prince Edward Island",
            "title": "ADS Level 5 - Client Services Representative - Veterinary Teaching Hospital - Atlantic Veterinary College - To Create a Casual List",
            "link": "https://www.upei.ca/hr/competition/131e25",
            "date": "Closing date: 2026-04-30T00:00:00",
            "new_since": "2025-11-27T22:51:52.217955"
        },
        {
            "school": "University of Prince Edward Island",
            "title": "MTS Level 6 - Animal Health Technician - Veterinary Teaching Hospital - Atlantic Veterinary College - To Create a Casual List",
            "link": "https://www.upei.ca/hr/competition/125e25",
            "date": "Closing date: 2026-04-30T00:00:00",
            "new_since": "2025-11-27T22:51:52.217955"
        },
        {
            "school": "University of Prince Edward Island",
            "title": "Tier II Canada Research Chair (CRC) in Equity in Nutrition, Physical Activity, or Health - Department of Applied Human Sciences - Faculty of Science",
            "link": "https://www.upei.ca/hr/competition/02a25",
            "date": "Closing date: 2025-03-12T00:00:00",
            "new_since": "2025-11-27T22:51:52.217955"
        },
        {
            "school": "University of Prince Edward Island",
            "title": "Canada Research Chair Tier II - Faculty of Education *Amended Closing Date*",
            "link": "https://www.upei.ca/hr/competition/40a24",
            "date": "Closing date: 2024-10-21T00:00:00",
            "new_since": "2025-11-27T22:51:52.217955"
        },
        {
            "school": "University of Prince Edward Island",
            "title": "MTS Level 7 - Medical Laboratory Technologist - Parasitology - Diagnostic Services - Atlantic Veterinary College",
            "link": "https://www.upei.ca/node/121674",
            "date": "Closing date: 2023-12-04T00:00:00",
            "new_since": "2025-11-27T22:51:52.217955"
        },
        {
            "title": "Resource Facilitator",
            "school": "College of the North Atlantic",
            "date": "2026-01-30T00:00:00",
            "link": "https://www.cna.nl.ca/Careers/opportunities/JobDetails?JobId=17628&JobSiteId=2,4",
            "new_since": "2026-01-30T22:52:28.067652"
        },
        {
            "title": "Employment Consultant (Career Development Specialist B)",
            "school": "College of the North Atlantic",
            "date": "2026-01-29T00:00:00",
            "link": "https://www.cna.nl.ca/Careers/opportunities/JobDetails?JobId=17632&JobSiteId=2,4",
            "new_since": "2026-01-30T22:52:28.067652"
        },
        {
            "title": "Early Childhood Educator",
            "school": "College of the North Atlantic",
            "date": "2026-01-29T00:00:00",
            "link": "https://www.cna.nl.ca/Careers/opportunities/JobDetails?JobId=17634&JobSiteId=2,4",
            "new_since": "2026-01-30T22:52:28.067652"
        },
        {
            "title": "Early Childhood Educator",
            "school": "College of the North Atlantic",
            "date": "2026-01-16T00:00:00",
            "link": "https://www.cna.nl.ca/Careers/opportunities/JobDetails?JobId=17616&JobSiteId=2,4",
            "new_since": "2026-01-20T22:52:44.992633"
        },
        {
            "title": "Instructor, Practical Nursing",
            "school": "College of the North Atlantic",
            "date": "2026-01-28T00:00:00",
            "link": "https://www.cna.nl.ca/Careers/opportunities/JobDetails?JobId=17492&JobSiteId=2,4",
            "new_since": "2026-01-30T22:52:28.067652"
        },
        {
            "title": "Instructional Coordinator, Practical Nursing",
            "school": "College of the North Atlantic",
            "date": "2026-01-28T00:00:00",
            "link": "https://www.cna.nl.ca/Careers/opportunities/JobDetails?JobId=17493&JobSiteId=2,4",
            "new_since": "2026-01-30T22:52:28.067652"
        },
        {
            "title": "Senior Manager of Administration Services",
            "school": "College of the North Atlantic",
            "date": "2026-01-27T00:00:00",
            "link": "https://www.cna.nl.ca/Careers/opportunities/JobDetails?JobId=17489&JobSiteId=2,4",
            "new_since": "2026-01-30T22:52:28.067652"
        },
        {
            "title": "Resource Facilitator",
            "school": "College of the North Atlantic",
            "date": "2026-01-27T00:00:00",
            "link": "https://www.cna.nl.ca/Careers/opportunities/JobDetails?JobId=17608&JobSiteId=2,4",
            "new_since": "2026-01-30T22:52:28.067652"
        },
        {
            "title": "Procurement Officer III",
            "school": "College of the North Atlantic",
            "date": "2026-01-22T00:00:00",
            "link": "https://www.cna.nl.ca/Careers/opportunities/JobDetails?JobId=17611&JobSiteId=2,4",
            "new_since": "2026-01-25T22:53:23.283003"
        },
        {
            "title": "Clerk Typist III",
            "school": "College of the North Atlantic",
            "date": "2026-01-26T00:00:00",
            "link": "https://www.cna.nl.ca/Careers/opportunities/JobDetails?JobId=17623&JobSiteId=2,4",
            "new_since": "2026-01-26T22:52:44.044730"
        },
        {
            "title": "Food Service Worker I",
            "school": "College of the North Atlantic",
            "date": "2026-01-20T00:00:00",
            "link": "https://www.cna.nl.ca/Careers/opportunities/JobDetails?JobId=17503&JobSiteId=2,4",
            "new_since": "2026-01-20T22:52:44.992633"
        },
        {
            "title": "Instructor, Aircraft Maintenance Engineering Technician Program (Avionics)",
            "school": "College of the North Atlantic",
            "date": "2025-12-01T00:00:00",
            "link": "https://www.cna.nl.ca/Careers/opportunities/JobDetails?JobId=17527&JobSiteId=2,4",
            "new_since": "2025-12-01T22:51:52.281454"
        },
        {
            "title": "EXPRESSION OF INTEREST - Instructor, French Conversation Beginner, Level 1, 2, and 3",
            "school": "College of the North Atlantic",
            "date": "2026-01-07T00:00:00",
            "link": "https://www.cna.nl.ca/Careers/opportunities/JobDetails?JobId=17584&JobSiteId=2,4",
            "new_since": "2026-01-09T22:52:18.890229"
        },
        {
            "title": "Early Childhood Educator",
            "school": "College of the North Atlantic",
            "date": "2025-12-01T00:00:00",
            "link": "https://www.cna.nl.ca/Careers/opportunities/JobDetails?JobId=17534&JobSiteId=2,4",
            "new_since": "2025-12-01T22:51:52.281454"
        },
        {
            "title": "Instructor, Heavy Duty Equipment Technician/Truck Transport Mechanic - Advanced Block Training",
            "school": "College of the North Atlantic",
            "date": "2025-11-18T00:00:00",
            "link": "https://www.cna.nl.ca/Careers/opportunities/JobDetails?JobId=17494&JobSiteId=2,4",
            "new_since": "2025-11-18T22:51:50.825159"
        },
        {
            "title": "Instructor, Millwright - CORRECTION NOTICE 07/28/2024",
            "school": "College of the North Atlantic",
            "date": "2025-07-28T00:00:00",
            "link": "https://www.cna.nl.ca/Careers/opportunities/JobDetails?JobId=16443&JobSiteId=2,4",
            "new_since": "2025-11-05T22:51:53.873136"
        },
        {
            "title": "Food Service Worker I",
            "school": "College of the North Atlantic",
            "date": "2025-11-07T00:00:00",
            "link": "https://www.cna.nl.ca/Careers/opportunities/JobDetails?JobId=17265&JobSiteId=2,4",
            "new_since": "2025-11-09T22:51:48.947863"
        },
        {
            "title": "Cook I",
            "school": "College of the North Atlantic",
            "date": "2025-10-29T00:00:00",
            "link": "https://www.cna.nl.ca/Careers/opportunities/JobDetails?JobId=17413&JobSiteId=2,4",
            "new_since": "2025-11-05T22:51:53.873136"
        },
        {
            "title": "Instructor, Mining Engineering Technician",
            "school": "College of the North Atlantic",
            "date": "2025-10-22T00:00:00",
            "link": "https://www.cna.nl.ca/Careers/opportunities/JobDetails?JobId=16970&JobSiteId=2,4",
            "new_since": "2025-11-05T22:51:53.873136"
        },
        {
            "title": "Instructor, Trades Bridging (Carpentry)",
            "school": "College of the North Atlantic",
            "date": "2025-10-17T00:00:00",
            "link": "https://www.cna.nl.ca/Careers/opportunities/JobDetails?JobId=17313&JobSiteId=2,4",
            "new_since": "2025-11-05T22:51:53.873136"
        },
        {
            "title": "Instructor, Instrumentation and Controls Technician",
            "school": "College of the North Atlantic",
            "date": "2025-08-29T00:00:00",
            "link": "https://www.cna.nl.ca/Careers/opportunities/JobDetails?JobId=17070&JobSiteId=2,4",
            "new_since": "2026-01-25T22:53:23.283003"
        },
        {
            "title": "Instructor, Power Sport Technician (formerly Small Equipment Service Technician)",
            "school": "College of the North Atlantic",
            "date": "2025-08-12T00:00:00",
            "link": "https://www.cna.nl.ca/Careers/opportunities/JobDetails?JobId=17225&JobSiteId=2,4",
            "new_since": "2025-11-05T22:51:53.873136"
        },
        {
            "title": "Accessibility Services Coordinator",
            "school": "College of the North Atlantic",
            "date": "2025-07-08T00:00:00",
            "link": "https://www.cna.nl.ca/Careers/opportunities/JobDetails?JobId=17062&JobSiteId=2,4",
            "new_since": "2025-11-05T22:51:53.873136"
        },
        {
            "title": "Resource Facilitator",
            "school": "College of the North Atlantic",
            "date": "2025-06-13T00:00:00",
            "link": "https://www.cna.nl.ca/Careers/opportunities/JobDetails?JobId=17065&JobSiteId=2,4",
            "new_since": "2025-11-05T22:51:53.873136"
        },
        {
            "title": "Lake O'Hara Lodge: Chef or Sous Chef",
            "school": "Holland College",
            "date": "December 19th, 2025",
            "link": "https://www.hollandcollege.com/jobfiles/chef-or-sous-chef-lake-ohara-lodge-16-dec-25.html",
            "new_since": "2025-12-19T22:51:40.688881"
        },
        {
            "title": "Government of PEI: Bilingual Customer Service Representative",
            "school": "Holland College",
            "date": "January 25th, 2026",
            "link": "https://www.hollandcollege.com/jobfiles/bilingual-customer-service-rep-govpei-jan20-2026.html",
            "new_since": "2026-01-25T22:53:23.284000"
        },
        {
            "title": "Zion Presbyterian Church: Children and Youth Ministry Lead",
            "school": "Holland College",
            "date": "January 25th, 2026",
            "link": "https://www.hollandcollege.com/jobfiles/children-youth-ministry-lead-zionpc-jan20-2026.html",
            "new_since": "2026-01-25T22:53:23.284000"
        },
        {
            "title": "PEI Alliance for Mental Well-Being: Training & Development Facilitator",
            "school": "Holland College",
            "date": "January 25th, 2026",
            "link": "https://www.hollandcollege.com/jobfiles/training-dev-facilitator-peialliance-mental-wellbeing-jan23-2026.html",
            "new_since": "2026-01-25T22:53:23.284000"
        },
        {
            "title": "Your Tooth Fairy: Full Time RDA - Summerside - 1805",
            "school": "Holland College",
            "date": "November 18th, 2025",
            "link": "https://www.hollandcollege.com/jobfiles/ft-rda-yourtoothfairy-nov18-2025.html",
            "new_since": "2025-11-18T22:51:50.825159"
        },
        {
            "title": "CIEE Council on Internation Educational Exchange: Culinary Intern",
            "school": "Holland College",
            "date": "December 19th, 2025",
            "link": "https://www.hollandcollege.com/jobfiles/culinary-intern-ciee-international-educational-exchange-11-dec-25.html",
            "new_since": "2025-12-19T22:51:40.688881"
        },
        {
            "title": "Interior Health: Rehabilitation Assistant",
            "school": "Holland College",
            "date": "December 19th, 2025",
            "link": "https://www.hollandcollege.com/jobfiles/rehab-assistant-interior-health-dec10-2025.html",
            "new_since": "2025-12-19T22:51:40.688881"
        },
        {
            "title": "Camp Triumph: Camp Counsellor (Full Summer)",
            "school": "Holland College",
            "date": "January 30th, 2026",
            "link": "https://www.hollandcollege.com/jobfiles/camp-counsellor-camp-triumph-jan29-2026.html",
            "new_since": "2026-01-30T22:52:28.067652"
        },
        {
            "title": "The Algonquin Resort: Cook 1",
            "school": "Holland College",
            "date": "December 20th, 2025",
            "link": "https://www.hollandcollege.com/jobfiles/cook-3-the-algonquin-resort-dec-19-25example-company.html",
            "new_since": "2025-12-20T22:51:39.848900"
        },
        {
            "title": "The Algonquin Resort: Cook 2",
            "school": "Holland College",
            "date": "December 20th, 2025",
            "link": "https://www.hollandcollege.com/jobfiles/cook-2-the-algonquin-resort-dec-19-25.html",
            "new_since": "2025-12-20T22:51:39.848900"
        },
        {
            "title": "The Algonquin Resort: Cook 1",
            "school": "Holland College",
            "date": "December 20th, 2025",
            "link": "https://www.hollandcollege.com/jobfiles/cook-1-the-algonquin-resort-dec-19-25.html",
            "new_since": "2025-12-20T22:51:39.848900"
        },
        {
            "title": "Master Packaging Inc. Borden: Master Packaging Inc. Borden - Summer Production Student",
            "school": "Holland College",
            "date": "January 30th, 2026",
            "link": "https://www.hollandcollege.com/jobfiles/summer-production-student-masterpackaging-jan29-2026.html",
            "new_since": "2026-01-30T22:52:28.067652"
        },
        {
            "title": "The Wickaninnnish Inn: Cook",
            "school": "Holland College",
            "date": "January 9th, 2026",
            "link": "https://www.hollandcollege.com/jobfiles/cook-the-wickaninnish-inn-jan-8-26.html",
            "new_since": "2026-01-09T22:52:18.890229"
        }
    ],
    "last_updated": "2026-01-30T22:52:28.067652"
}